xwacommap.py
xwacommap-0.1.0.dist-info/entry_points.txt
xwacommap-0.1.0.dist-info/WHEEL
xwacommap-0.1.0.dist-info/METADATA
xwacommap-0.1.0.dist-info/RECORD
