Metadata-Version: 2.1
Name: xwacommap
Version: 0.1.0
Summary: Interactive utility to map Wacom tablets to screen areas
Home-page: https://edugit.org/nik/xwacommap
License: Apache-2.0
Author: Dominik George
Author-email: nik@naturalnet.de
Requires-Python: >=3.7,<4.0
Classifier: License :: OSI Approved :: Apache Software License
Classifier: Programming Language :: Python :: 3
Classifier: Programming Language :: Python :: 3.7
Classifier: Programming Language :: Python :: 3.8
Classifier: Programming Language :: Python :: 3.9
Requires-Dist: python-xrectsel (>=1.3,<2.0)
Requires-Dist: sh (>=1.14.1,<2.0.0)
Project-URL: Repository, https://edugit.org/nik/xwacommap
